ay_charts/AyBar.py
ay_charts/AyBox.py
ay_charts/AyCard.py
ay_charts/AyChart.py
ay_charts/AyCharts.py
ay_charts/AyColumn.py
ay_charts/AyCorr.py
ay_charts/AyHistogram.py
ay_charts/AyPie.py
ay_charts/AyScatter.py
ay_charts/__init__.py
ay_charts/_imports_.py
ay_charts/ay_charts.min.js
ay_charts/ay_charts.min.js.map
ay_charts/metadata.json
ay_charts/package-info.json
ay_charts-0.0.1.dist-info/LICENSE
ay_charts-0.0.1.dist-info/METADATA
ay_charts-0.0.1.dist-info/WHEEL
ay_charts-0.0.1.dist-info/top_level.txt
ay_charts-0.0.1.dist-info/RECORD
