Metadata-Version: 2.1
Name: ay-charts
Version: 0.0.1
Summary: Dash-based charts for data visualization
Author: Anya Ip <anyakurapica@gmail.com>
License: MIT
Classifier: Framework :: Dash
License-File: LICENSE
